hebrew_tokenizer/__init__.py
hebrew_tokenizer/api.py
hebrew_tokenizer/groups.py
hebrew_tokenizer/lexicon.py
hebrew_tokenizer/tokenizer.py
tests/__init__.py
tests/tokenizer_tests.py
hebrew_tokenizer-1.1.0.dist-info/LICENSE
hebrew_tokenizer-1.1.0.dist-info/METADATA
hebrew_tokenizer-1.1.0.dist-info/WHEEL
hebrew_tokenizer-1.1.0.dist-info/top_level.txt
hebrew_tokenizer-1.1.0.dist-info/RECORD
