Metadata-Version: 2.1
Name: hebrew-tokenizer
Version: 1.1.0
Summary: A very simple python tokenizer for Hebrew text
Home-page: https://github.com/yontilevin/hebrew_tokenizer
Author: Yonti Levin
Author-email: therealyontilevin@gmail.com
License: MIT
Platform: UNKNOWN
Classifier: License :: OSI Approved :: MIT License
Classifier: Programming Language :: Python
Classifier: Operating System :: OS Independent
Requires-Python: >=2.6, !=3.0.*, !=3.1.*, !=3.2.*, !=3.3.*
